{
    "film-and-the-environment": {
        "course_name": "Film and the Environment: Cinematic Notions and Representations of the Future",
        "courses": "ENG 492 & FL 495",
        "form_link": "https://docs.google.com/presentation/d/1-aDeVnUXjxogz2Zdl_zG4A5rRZJ5oLuvdP-G1S9qf6M/edit#slide=id.gd9d803df46_2_81"
    },
    "wpws": {
        "course_name": "Wicked Problems, Wolfpack Solutions Edition",
        "courses": "",
        "form_link": ""
    },
    "all": {
        "course_name": "",
        "courses": "",
        "form_link": ""
    }
}